{
  "generated": "2026-05-12",
  "items": [
    {
      "billNo": "2218919",
      "title": "인공지능 발전과 신뢰 기반 조성 등에 관한 기본법 일부개정법률안",
      "category": "국민 생활 직결 분야",
      "summary": "인공지능 발전 기반 조성",
      "date": "2026-05-11",
      "committee": "",
      "proposer": "김대식의원 등 10인",
      "procResult": "",
      "sourceUrl": ""
    },
    {
      "billNo": "2218912",
      "title": "노동조합 및 노동관계조정법 일부개정법률안",
      "category": "국민 생활 직결 분야",
      "summary": "노동관계 조정법 개정안",
      "date": "2026-05-11",
      "committee": "",
      "proposer": "박수민의원 등 10인",
      "procResult": "",
      "sourceUrl": ""
    },
    {
      "billNo": "2218911",
      "title": "폐기물관리법 일부개정법률안",
      "category": "국민 생활 직결 분야",
      "summary": "폐기물 관리 법안 개정안",
      "date": "2026-05-11",
      "committee": "",
      "proposer": "문진석의원 등 10인",
      "procResult": "",
      "sourceUrl": ""
    },
    {
      "billNo": "2218904",
      "title": "공동주택관리법 일부개정법률안",
      "category": "국민 생활 직결 분야",
      "summary": "공동주택 관리법 개정안",
      "date": "2026-05-08",
      "committee": "국토교통위원회",
      "proposer": "이건태의원 등 11인",
      "procResult": "",
      "sourceUrl": ""
    },
    {
      "billNo": "2218899",
      "title": "아동학대범죄의 처벌 등에 관한 특례법 일부개정법률안",
      "category": "국민 생활 직결 분야",
      "summary": "아동학대 범죄 처벌 법안",
      "date": "2026-05-08",
      "committee": "법제사법위원회",
      "proposer": "김기표의원 등 11인",
      "procResult": "",
      "sourceUrl": ""
    },
    {
      "billNo": "2218893",
      "title": "주거기본법 일부개정법률안",
      "category": "국민 생활 직결 분야",
      "summary": "주거 기본법 일부 개정",
      "date": "2026-05-08",
      "committee": "국토교통위원회",
      "proposer": "김미애의원 등 11인",
      "procResult": "",
      "sourceUrl": ""
    },
    {
      "billNo": "2218826",
      "title": "저출산·고령사회기본법 일부개정법률안",
      "category": "국민 생활 직결 분야",
      "summary": "저출산 고령사회 기본법",
      "date": "2026-05-06",
      "committee": "보건복지위원회",
      "proposer": "안상훈의원 등 11인",
      "procResult": "",
      "sourceUrl": ""
    },
    {
      "billNo": "2218825",
      "title": "의료·요양 등 지역 돌봄의 통합지원에 관한 법률 일부개정법률안",
      "category": "국민 생활 직결 분야",
      "summary": "지역 돌봄 통합지원 법안",
      "date": "2026-05-06",
      "committee": "보건복지위원회",
      "proposer": "안상훈의원 등 11인",
      "procResult": "",
      "sourceUrl": ""
    },
    {
      "billNo": "2218824",
      "title": "응급의료에 관한 법률 일부개정법률안",
      "category": "국민 생활 직결 분야",
      "summary": "응급의료 관련 법안",
      "date": "2026-05-06",
      "committee": "보건복지위원회",
      "proposer": "장종태의원 등 11인",
      "procResult": "",
      "sourceUrl": ""
    },
    {
      "billNo": "2218812",
      "title": "국민기초생활 보장법 일부개정법률안",
      "category": "국민 생활 직결 분야",
      "summary": "국민기초생활 보장법 개정",
      "date": "2026-05-06",
      "committee": "보건복지위원회",
      "proposer": "김문수의원 등 12인",
      "procResult": "",
      "sourceUrl": ""
    },
    {
      "billNo": "2218788",
      "title": "장기공공임대주택 입주자 삶의 질 향상 지원법 일부개정법률안",
      "category": "국민 생활 직결 분야",
      "summary": "장기 공공임대주택 지원",
      "date": "2026-05-04",
      "committee": "국토교통위원회",
      "proposer": "전현희의원 등 10인",
      "procResult": "",
      "sourceUrl": ""
    }
  ]
}