{
  "generated": "2026-05-15",
  "items": [
    {
      "billNo": "2218978",
      "title": "도시 및 주거환경정비법 일부개정법률안",
      "category": "국민 생활 직결 분야",
      "summary": "주거 환경 개선 지원해요",
      "date": "2026-05-14",
      "committee": "",
      "proposer": "김희정의원 등 11인",
      "procResult": "",
      "sourceUrl": ""
    },
    {
      "billNo": "2218976",
      "title": "주택도시기금법 일부개정법률안",
      "category": "국민 생활 직결 분야",
      "summary": "주택도시기금 지원해요",
      "date": "2026-05-14",
      "committee": "",
      "proposer": "조은희의원 등 12인",
      "procResult": "",
      "sourceUrl": ""
    },
    {
      "billNo": "2218893",
      "title": "주거기본법 일부개정법률안",
      "category": "국민 생활 직결 분야",
      "summary": "주거기본권 보장해요",
      "date": "2026-05-08",
      "committee": "국토교통위원회",
      "proposer": "김미애의원 등 11인",
      "procResult": "",
      "sourceUrl": ""
    }
  ]
}